{
  "updatedAt": "2026-06-25T22:00:15Z",
  "mods": [
    {
      "platform": "nexus",
      "mod_id": "17070",
      "mod_name": "TGGs Sexy Black Lingerie",
      "mod_url": "https://www.nexusmods.com/starfield/mods/17070",
      "image_url": "https://staticdelivery.nexusmods.com/mods/4187/images/17070/17070-1778687683-1944088645.png",
      "total_downloads": 416,
      "unique_downloads": 372,
      "daily_downloads": 2,
      "likes": 24,
      "views": 0
    },
    {
      "platform": "nexus",
      "mod_id": "17126",
      "mod_name": "THE TERMINUS",
      "mod_url": "https://www.nexusmods.com/starfield/mods/17126",
      "image_url": "https://staticdelivery.nexusmods.com/mods/4187/images/17126/17126-1779071888-668213181.png",
      "total_downloads": 1399,
      "unique_downloads": 708,
      "daily_downloads": 4,
      "likes": 28,
      "views": 0
    },
    {
      "platform": "nexus",
      "mod_id": "17251",
      "mod_name": "Nebula Protocol Suit",
      "mod_url": "https://www.nexusmods.com/starfield/mods/17251",
      "image_url": "https://staticdelivery.nexusmods.com/mods/4187/images/17251/17251-1779804128-1212319096.png",
      "total_downloads": 383,
      "unique_downloads": 346,
      "daily_downloads": 2,
      "likes": 18,
      "views": 0
    },
    {
      "platform": "nexus",
      "mod_id": "17285",
      "mod_name": "CASSILIAs SOUL",
      "mod_url": "https://www.nexusmods.com/starfield/mods/17285",
      "image_url": "https://staticdelivery.nexusmods.com/mods/4187/images/17285/17285-1780066726-1556236471.png",
      "total_downloads": 326,
      "unique_downloads": 235,
      "daily_downloads": 1,
      "likes": 7,
      "views": 0
    },
    {
      "platform": "nexus",
      "mod_id": "17362",
      "mod_name": "TGG Cloth-DVA bodysuit",
      "mod_url": "https://www.nexusmods.com/starfield/mods/17362",
      "image_url": "https://staticdelivery.nexusmods.com/mods/4187/images/17362/17362-1780583435-1843506797.png",
      "total_downloads": 472,
      "unique_downloads": 367,
      "daily_downloads": 3,
      "likes": 24,
      "views": 0
    },
    {
      "platform": "nexus",
      "mod_id": "17387",
      "mod_name": "Cassilia's Old Constellation Uniform",
      "mod_url": "https://www.nexusmods.com/starfield/mods/17387",
      "image_url": "https://staticdelivery.nexusmods.com/mods/4187/images/17387/17387-1780911831-1036925630.png",
      "total_downloads": 2427,
      "unique_downloads": 1827,
      "daily_downloads": 85,
      "likes": 103,
      "views": 0
    },
    {
      "platform": "nexus",
      "mod_id": "17461",
      "mod_name": "CASSILIAs POWER FIST",
      "mod_url": "https://www.nexusmods.com/starfield/mods/17461",
      "image_url": "https://staticdelivery.nexusmods.com/mods/4187/images/17461/17461-1781423403-782378004.png",
      "total_downloads": 385,
      "unique_downloads": 349,
      "daily_downloads": 8,
      "likes": 13,
      "views": 0
    },
    {
      "platform": "nexus",
      "mod_id": "17479",
      "mod_name": "CPF-UC VANGUARD POWER FIST MK2",
      "mod_url": "https://www.nexusmods.com/starfield/mods/17479",
      "image_url": "https://staticdelivery.nexusmods.com/mods/4187/images/17479/17479-1781621856-615818030.png",
      "total_downloads": 126,
      "unique_downloads": 121,
      "daily_downloads": 1,
      "likes": 5,
      "views": 0
    },
    {
      "platform": "nexus",
      "mod_id": "17489",
      "mod_name": "CPF-STARBORN POWER FIST UNITY",
      "mod_url": "https://www.nexusmods.com/starfield/mods/17489",
      "image_url": "https://staticdelivery.nexusmods.com/mods/4187/images/17489/17489-1781703543-86285545.png",
      "total_downloads": 153,
      "unique_downloads": 151,
      "daily_downloads": 2,
      "likes": 7,
      "views": 0
    },
    {
      "platform": "nexus",
      "mod_id": "17500",
      "mod_name": "CPF-STARBORN  POWER FIST OMEGA",
      "mod_url": "https://www.nexusmods.com/starfield/mods/17500",
      "image_url": "https://staticdelivery.nexusmods.com/mods/4187/images/17500/17500-1781842553-1785018540.png",
      "total_downloads": 142,
      "unique_downloads": 129,
      "daily_downloads": 3,
      "likes": 5,
      "views": 0
    },
    {
      "platform": "nexus",
      "mod_id": "17501",
      "mod_name": "CPF-CRIMSON FLEET POWER FIST HELLHOUND",
      "mod_url": "https://www.nexusmods.com/starfield/mods/17501",
      "image_url": "https://staticdelivery.nexusmods.com/mods/4187/images/17501/17501-1781854590-1310759891.png",
      "total_downloads": 85,
      "unique_downloads": 81,
      "daily_downloads": 1,
      "likes": 3,
      "views": 0
    },
    {
      "platform": "nexus",
      "mod_id": "17521",
      "mod_name": "CASSILIAs Trainning Dummy",
      "mod_url": "https://www.nexusmods.com/starfield/mods/17521",
      "image_url": "https://staticdelivery.nexusmods.com/mods/4187/images/17521/17521-1782131371-2132304027.png",
      "total_downloads": 25,
      "unique_downloads": 23,
      "daily_downloads": 2,
      "likes": 2,
      "views": 0
    }
  ]
}
